MANIFEST.in
README.mkd
setup.py
SBlog.egg-info/PKG-INFO
SBlog.egg-info/SOURCES.txt
SBlog.egg-info/dependency_links.txt
SBlog.egg-info/entry_points.txt
SBlog.egg-info/requires.txt
SBlog.egg-info/top_level.txt
sblog/__init__.py
sblog/_compat.py
sblog/app.py
sblog/config.py
sblog/log.py
sblog/main.py
sblog/namespace.py
sblog/utils.py
sblog.egg-info/SOURCES.txt
sblog/_themes/default/feed.xml
sblog/_themes/default/index.html
sblog/_themes/default/layout.html
sblog/_themes/default/post.html
sblog/_themes/default/sidebar-left.html
sblog/_themes/default/sidebar-right.html
sblog/_themes/default/tag.html
sblog/_themes/default/assets/sblog.css
sblog/_themes/default/assets/sblog.styl
sblog/_themes/default/assets/yue.styl
sblog/_themes/default/static/sblog.css
sblog/bin/__init__.py
sblog/bin/cli.py
sblog/readers/__init__.py
sblog/readers/_base.py
sblog/readers/markdown.py
sblog/readers/post.py
sblog/writers/__init__.py
sblog/writers/_base.py
sblog/writers/feed.py
sblog/writers/index.py
sblog/writers/meta.py
sblog/writers/post.py
sblog/writers/tag.py