Metadata-Version: 1.1
Name: sblog
Version: 2.0.0
Summary: A simple static blog generator.
Home-page: blog.xiaoba.me
Author: Yuwei Ba
Author-email: xiaobayuwei@gmail.com
License: MIT License
Keywords: SBlog,markdown,Static Blog
Platform: UNKNOWN
Classifier: Development Status :: 3 - Alpha
Classifier: Environment :: Console
Classifier: License :: OSI Approved :: MIT License
Classifier: Operating System :: POSIX
Classifier: Programming Language :: Python
